perpetual-0.10.0.dist-info/METADATA
perpetual-0.10.0.dist-info/WHEEL
perpetual-0.10.0.dist-info/licenses/LICENSE
perpetual/__init__.py
perpetual/booster.py
perpetual/data.py
perpetual/perpetual.cp310-win_amd64.pyd
perpetual/serialize.py
perpetual/sklearn.py
perpetual/types.py
perpetual/utils.py
perpetual-0.10.0.dist-info/RECORD
