Metadata-Version: 2.4
Name: perpetual
Version: 0.10.0
Classifier: Programming Language :: Rust
Classifier: Programming Language :: Python :: 3
Classifier: Programming Language :: Python :: 3.9
Classifier: Programming Language :: Python :: 3.10
Classifier: Programming Language :: Python :: 3.11
Classifier: Programming Language :: Python :: 3.12
Classifier: Programming Language :: Python :: 3.13
Requires-Dist: numpy
Requires-Dist: typing-extensions
Requires-Dist: black ; extra == 'dev'
Requires-Dist: pandas ; extra == 'dev'
Requires-Dist: polars ; extra == 'dev'
Requires-Dist: pyarrow ; extra == 'dev'
Requires-Dist: maturin ; extra == 'dev'
Requires-Dist: pytest ; extra == 'dev'
Requires-Dist: seaborn ; extra == 'dev'
Requires-Dist: scikit-learn ; extra == 'dev'
Requires-Dist: mkdocs-material ; extra == 'dev'
Requires-Dist: mkdocstrings[python] ; extra == 'dev'
Requires-Dist: mkdocs-autorefs ; extra == 'dev'
Requires-Dist: ruff ; extra == 'dev'
Provides-Extra: dev
License-File: LICENSE
Summary: A self-generalizing gradient boosting machine that doesn't need hyperparameter optimization
Keywords: rust,perpetual,machine learning,tree model,decision tree,gradient boosted decision tree,gradient boosting machine
Home-Page: https://perpetual-ml.com
Author-email: Mutlu Simsek <mutlusims3k@gmail.com>, Serkan Korkmaz <serkor1@duck.com>, Pieter Pel <pelpieter@gmail.com>
Requires-Python: >=3.9
